MANIFEST.in
README.md
requirements.txt
setup.cfg
setup.py
biocertainty/__init__.py
biocertainty/certainty.py
biocertainty/micropublication.py
biocertainty/nanopublication.py
biocertainty/seeker.py
biocertainty.egg-info/PKG-INFO
biocertainty.egg-info/SOURCES.txt
biocertainty.egg-info/dependency_links.txt
biocertainty.egg-info/not-zip-safe
biocertainty.egg-info/top_level.txt
data/model.h5
data/model.json
data/training_set.csv
docs/index.md